mdu_pytools/__init__.py
mdu_pytools/merge_ngs_lanes.py
mdu_pytools/sra_uploads.py
mdu_pytools-0.2.0.dist-info/METADATA
mdu_pytools-0.2.0.dist-info/WHEEL
mdu_pytools-0.2.0.dist-info/entry_points.txt
mdu_pytools-0.2.0.dist-info/top_level.txt
mdu_pytools-0.2.0.dist-info/RECORD
