Metadata-Version: 2.1
Name: mdu-pytools
Version: 0.2.0
Summary: Small tools/scripts written in Python for MDU
Home-page: https://github.com/MDU-PHL/mdu-pytools
Author: MDU Bioinformatics
Author-email: andersgs@gmail.com
License: UNKNOWN
Project-URL: Bug Reports, https://github.com/MDU-PHL/mdu-pytools/issues
Project-URL: Source, https://github.com/MDU-PHL/mdu-pytools/
Keywords: bioinformatics microbial-genomics
Platform: UNKNOWN
Classifier: Development Status :: 4 - Beta
Classifier: Intended Audience :: Science/Research
Classifier: Topic :: Scientific/Engineering :: Bio-Informatics
Classifier: License :: OSI Approved :: GNU Lesser General Public License v3 (LGPLv3)
Classifier: Programming Language :: Python :: Implementation :: CPython
Classifier: Programming Language :: Python :: 3.6
Classifier: Programming Language :: Python :: 3.7
Requires-Python: >=3.6, <4
Requires-Dist: pandas
Requires-Dist: loguru
Requires-Dist: click
Requires-Dist: tqdm
Provides-Extra: dev
Requires-Dist: pre-commit ; extra == 'dev'
Requires-Dist: pipenv ; extra == 'dev'
Requires-Dist: bumpversion ; extra == 'dev'
Requires-Dist: invoke ; extra == 'dev'
Provides-Extra: test
Requires-Dist: pytest ; extra == 'test'
Requires-Dist: pytest-cov ; extra == 'test'
